{
  "@context" : "http://iiif.io/api/image/3/context.json",
  "protocol" : "http://iiif.io/api/image",
  "width" : 7892,
  "height" : 9867,
  "sizes" : [
     { "width" : 123, "height" : 154 },
     { "width" : 246, "height" : 308 },
     { "width" : 493, "height" : 616 },
     { "width" : 986, "height" : 1233 },
     { "width" : 1973, "height" : 2466 },
     { "width" : 3946, "height" : 4933 }
  ],
  "tiles" : [
     { "width" : 256, "height" : 256, "scaleFactors" : [ 1, 2, 4, 8, 16, 32, 64 ] }
  ],
  "id" : "http://localhost/iiif/lossless/gm_00045001.tif",
  "type": "ImageService3",
  "profile" : "level2",
  "maxWidth" : 50000,
  "maxHeight" : 50000,
  "extraQualities": ["color","gray","bitonal"],
  "extraFormats": ["webp"],
  "extraFeatures": ["regionByPct","sizeByForcedWh","sizeByWh","sizeAboveFull","sizeUpscaling","rotationBy90s","mirroring"]
}